{"Data":[{"Id":2409535,"Problem":{"Method":"Feet follow hands","Name":"ALI\u0027S SPLIT CONTINUITY","Grade":"6B+","UserGrade":"6B+","MoonBoardConfiguration":null,"MoonBoardConfigurationId":0,"Setter":{"Id":"B0912D73-B40C-425B-84CB-5D979A1F77F7","Nickname":"Alasdair Kennedy","Firstname":"Alasdair","Lastname":"Kennedy","City":"Bristol","Country":"UK ","ProfileImageUrl":"/Content/Account/Images/default-profile.png?636442311928344740"},"FirstAscender":false,"Rating":0,"UserRating":2,"Repeats":215,"Attempts":0,"Holdsetup":{"Id":1,"Description":"MoonBoard 2016","Setby":null,"DateInserted":null,"DateUpdated":null,"DateDeleted":null,"Holdsets":null,"MoonBoardConfigurations":null,"HoldLayoutId":0,"AllowClimbMethods":false},"IsBenchmark":false,"Moves":[{"Id":1521078,"Description":"K5","IsStart":true,"IsEnd":false},{"Id":1521079,"Description":"I5","IsStart":true,"IsEnd":false},{"Id":1521080,"Description":"J8","IsStart":false,"IsEnd":false},{"Id":1521081,"Description":"G8","IsStart":false,"IsEnd":false},{"Id":1521082,"Description":"I10","IsStart":false,"IsEnd":false},{"Id":1521083,"Description":"E10","IsStart":false,"IsEnd":false},{"Id":1521084,"Description":"G13","IsStart":false,"IsEnd":false},{"Id":1521085,"Description":"E15","IsStart":false,"IsEnd":false},{"Id":1521086,"Description":"I18","IsStart":false,"IsEnd":true}],"Holdsets":null,"Locations":[{"Id":0,"Holdset":null,"Description":null,"X":295,"Y":488,"Color":"0x0000FF","Rotation":0,"Type":0,"HoldNumber":null,"Direction":0,"DirectionString":"N"},{"Id":0,"Holdset":null,"Description":null,"X":295,"Y":238,"Color":"0x0000FF","Rotation":0,"Type":0,"HoldNumber":null,"Direction":0,"DirectionString":"N"},{"Id":0,"Holdset":null,"Description":null,"X":395,"Y":588,"Color":"0x0000FF","Rotation":0,"Type":0,"HoldNumber":null,"Direction":0,"DirectionString":"N"},{"Id":0,"Holdset":null,"Description":null,"X":395,"Y":338,"Color":"0x0000FF","Rotation":0,"Type":0,"HoldNumber":null,"Direction":0,"DirectionString":"N"},{"Id":0,"Holdset":null,"Description":null,"X":495,"Y":738,"Color":"0x00FF00","Rotation":0,"Type":0,"HoldNumber":null,"Direction":0,"DirectionString":"N"},{"Id":0,"Holdset":null,"Description":null,"X":495,"Y":488,"Color":"0x0000FF","Rotation":0,"Type":0,"HoldNumber":null,"Direction":0,"DirectionString":"N"},{"Id":0,"Holdset":null,"Description":null,"X":495,"Y":88,"Color":"0xFF0000","Rotation":0,"Type":0,"HoldNumber":null,"Direction":0,"DirectionString":"N"},{"Id":0,"Holdset":null,"Description":null,"X":545,"Y":586,"Color":"0x0000FF","Rotation":0,"Type":0,"HoldNumber":null,"Direction":0,"DirectionString":"N"},{"Id":0,"Holdset":null,"Description":null,"X":595,"Y":738,"Color":"0x00FF00","Rotation":0,"Type":0,"HoldNumber":null,"Direction":0,"DirectionString":"N"}],"RepeatText":"215 climbers  have repeated this problem","NumberOfTries":"FLASHED","NameForUrl":"ali-s-split-continuity","Id":23097,"ApiId":23097,"DateInserted":"\/Date(1463913005000)\/","DateUpdated":null,"DateDeleted":null,"DateTimeString":"22 May 2016 11:30"},"Attempts":0,"Grade":"6B+","NumberOfTries":"Flashed","Rating":0,"DateClimbed":"\/Date(1500505200000)\/","DateClimbedAsString":"20 Jul 2017","DateInserted":"\/Date(1500592213000)\/","Comment":"","User":{"Id":"6BE4A8C1-02C7-4BA4-9589-769ED0B3571C","Nickname":"Sean Christopherson","Firstname":"Sean","Lastname":"Christopherson","City":"Portland","Country":"USA","ProfileImageUrl":"/Content/Account/Images/default-profile.png?636442311928498584"}},{"Id":2409571,"Problem":{"Method":"Feet follow hands","Name":"LESS IS MORE...","Grade":"6B+","UserGrade":"6B+","MoonBoardConfiguration":null,"MoonBoardConfigurationId":0,"Setter":{"Id":"C2338857-12FD-4846-B850-EA795B83B240","Nickname":"Fox","Firstname":"Dale","Lastname":"Cebula","City":"Northamptonshire","Country":"United Kingdom","ProfileImageUrl":"/Content/Account/Users/Profile/C2338857-12FD-4846-B850-EA795B83B240.png?636442311928498584"},"FirstAscender":false,"Rating":0,"UserRating":2,"Repeats":201,"Attempts":0,"Holdsetup":{"Id":1,"Description":"MoonBoard 2016","Setby":null,"DateInserted":null,"DateUpdated":null,"DateDeleted":null,"Holdsets":null,"MoonBoardConfigurations":null,"HoldLayoutId":0,"AllowClimbMethods":false},"IsBenchmark":false,"Moves":[{"Id":1519451,"Description":"F5","IsStart":true,"IsEnd":false},{"Id":1519452,"Description":"E8","IsStart":false,"IsEnd":false},{"Id":1519453,"Description":"H10","IsStart":false,"IsEnd":false},{"Id":1519454,"Description":"E13","IsStart":false,"IsEnd":false},{"Id":1519455,"Description":"E16","IsStart":false,"IsEnd":false},{"Id":1519456,"Description":"E18","IsStart":false,"IsEnd":true}],"Holdsets":null,"Locations":[{"Id":0,"Holdset":null,"Description":null,"X":295,"Y":588,"Color":"0x0000FF","Rotation":0,"Type":0,"HoldNumber":null,"Direction":0,"DirectionString":"N"},{"Id":0,"Holdset":null,"Description":null,"X":295,"Y":338,"Color":"0x0000FF","Rotation":0,"Type":0,"HoldNumber":null,"Direction":0,"DirectionString":"N"},{"Id":0,"Holdset":null,"Description":null,"X":295,"Y":188,"Color":"0x0000FF","Rotation":0,"Type":0,"HoldNumber":null,"Direction":0,"DirectionString":"N"},{"Id":0,"Holdset":null,"Description":null,"X":295,"Y":88,"Color":"0xFF0000","Rotation":0,"Type":0,"HoldNumber":null,"Direction":0,"DirectionString":"N"},{"Id":0,"Holdset":null,"Description":null,"X":345,"Y":736,"Color":"0x00FF00","Rotation":0,"Type":0,"HoldNumber":null,"Direction":0,"DirectionString":"N"},{"Id":0,"Holdset":null,"Description":null,"X":445,"Y":486,"Color":"0x0000FF","Rotation":0,"Type":0,"HoldNumber":null,"Direction":0,"DirectionString":"N"}],"RepeatText":"201 climbers  have repeated this problem","NumberOfTries":"FLASHED","NameForUrl":"less-is-more","Id":20588,"ApiId":20588,"DateInserted":"\/Date(1460391991000)\/","DateUpdated":null,"DateDeleted":null,"DateTimeString":"11 Apr 2016 17:26"},"Attempts":0,"Grade":"6B+","NumberOfTries":"Flashed","Rating":3,"DateClimbed":"\/Date(1500505200000)\/","DateClimbedAsString":"20 Jul 2017","DateInserted":"\/Date(1500597044000)\/","Comment":"","User":{"Id":"6BE4A8C1-02C7-4BA4-9589-769ED0B3571C","Nickname":"Sean Christopherson","Firstname":"Sean","Lastname":"Christopherson","City":"Portland","Country":"USA","ProfileImageUrl":"/Content/Account/Images/default-profile.png?636442311928654866"}},{"Id":2409574,"Problem":{"Method":"Feet follow hands","Name":"AMBERJACK","Grade":"6B+","UserGrade":"6B+","MoonBoardConfiguration":null,"MoonBoardConfigurationId":0,"Setter":{"Id":"6B0BC442-19B3-42F5-A856-7CEBAEB54832","Nickname":"Bryant Noble","Firstname":"Bryant","Lastname":"Noble","City":"Athens","Country":"USA","ProfileImageUrl":"/Content/Account/Images/default-profile.png?636442311928654866"},"FirstAscender":false,"Rating":0,"UserRating":2,"Repeats":190,"Attempts":0,"Holdsetup":{"Id":1,"Description":"MoonBoard 2016","Setby":null,"DateInserted":null,"DateUpdated":null,"DateDeleted":null,"Holdsets":null,"MoonBoardConfigurations":null,"HoldLayoutId":0,"AllowClimbMethods":false},"IsBenchmark":false,"Moves":[{"Id":1527138,"Description":"F5","IsStart":true,"IsEnd":false},{"Id":1527139,"Description":"E8","IsStart":false,"IsEnd":false},{"Id":1527140,"Description":"B11","IsStart":false,"IsEnd":false},{"Id":1527141,"Description":"E13","IsStart":false,"IsEnd":false},{"Id":1527142,"Description":"E15","IsStart":false,"IsEnd":false},{"Id":1527143,"Description":"D17","IsStart":false,"IsEnd":false},{"Id":1527144,"Description":"B18","IsStart":false,"IsEnd":true}],"Holdsets":null,"Locations":[{"Id":0,"Holdset":null,"Description":null,"X":145,"Y":86,"Color":"0xFF0000","Rotation":0,"Type":0,"HoldNumber":null,"Direction":0,"DirectionString":"N"},{"Id":0,"Holdset":null,"Description":null,"X":145,"Y":436,"Color":"0x0000FF","Rotation":0,"Type":0,"HoldNumber":null,"Direction":0,"DirectionString":"N"},{"Id":0,"Holdset":null,"Description":null,"X":245,"Y":136,"Color":"0x0000FF","Rotation":0,"Type":0,"HoldNumber":null,"Direction":0,"DirectionString":"N"},{"Id":0,"Holdset":null,"Description":null,"X":295,"Y":588,"Color":"0x0000FF","Rotation":0,"Type":0,"HoldNumber":null,"Direction":0,"DirectionString":"N"},{"Id":0,"Holdset":null,"Description":null,"X":295,"Y":338,"Color":"0x0000FF","Rotation":0,"Type":0,"HoldNumber":null,"Direction":0,"DirectionString":"N"},{"Id":0,"Holdset":null,"Description":null,"X":295,"Y":238,"Color":"0x0000FF","Rotation":0,"Type":0,"HoldNumber":null,"Direction":0,"DirectionString":"N"},{"Id":0,"Holdset":null,"Description":null,"X":345,"Y":736,"Color":"0x00FF00","Rotation":0,"Type":0,"HoldNumber":null,"Direction":0,"DirectionString":"N"}],"RepeatText":"190 climbers  have repeated this problem","NumberOfTries":"FLASHED","NameForUrl":"amberjack","Id":38058,"ApiId":38058,"DateInserted":"\/Date(1473458178000)\/","DateUpdated":null,"DateDeleted":null,"DateTimeString":"09 Sep 2016 22:56"},"Attempts":0,"Grade":"6B+","NumberOfTries":"Flashed","Rating":3,"DateClimbed":"\/Date(1500505200000)\/","DateClimbedAsString":"20 Jul 2017","DateInserted":"\/Date(1500597154000)\/","Comment":"","User":{"Id":"6BE4A8C1-02C7-4BA4-9589-769ED0B3571C","Nickname":"Sean Christopherson","Firstname":"Sean","Lastname":"Christopherson","City":"Portland","Country":"USA","ProfileImageUrl":"/Content/Account/Images/default-profile.png?636442311928811128"}},{"Id":2409577,"Problem":{"Method":"Feet follow hands","Name":"RUSSEL","Grade":"6B+","UserGrade":"6B+","MoonBoardConfiguration":null,"MoonBoardConfigurationId":0,"Setter":{"Id":"88EC841E-81AC-45CC-A0D5-3AD29C307244","Nickname":"Beth Jennings","Firstname":"Beth","Lastname":"Jennings","City":"Sheffield","Country":"UK","ProfileImageUrl":"/Content/Account/Images/default-profile.png?636442311928967391"},"FirstAscender":false,"Rating":0,"UserRating":2,"Repeats":204,"Attempts":0,"Holdsetup":{"Id":1,"Description":"MoonBoard 2016","Setby":null,"DateInserted":null,"DateUpdated":null,"DateDeleted":null,"Holdsets":null,"MoonBoardConfigurations":null,"HoldLayoutId":0,"AllowClimbMethods":false},"IsBenchmark":false,"Moves":[{"Id":1526509,"Description":"F5","IsStart":true,"IsEnd":false},{"Id":1526510,"Description":"I4","IsStart":true,"IsEnd":false},{"Id":1526511,"Description":"H8","IsStart":false,"IsEnd":false},{"Id":1526512,"Description":"E10","IsStart":false,"IsEnd":false},{"Id":1526513,"Description":"G13","IsStart":false,"IsEnd":false},{"Id":1526514,"Description":"E15","IsStart":false,"IsEnd":false},{"Id":1526515,"Description":"E18","IsStart":false,"IsEnd":true}],"Holdsets":null,"Locations":[{"Id":0,"Holdset":null,"Description":null,"X":295,"Y":488,"Color":"0x0000FF","Rotation":0,"Type":0,"HoldNumber":null,"Direction":0,"DirectionString":"N"},{"Id":0,"Holdset":null,"Description":null,"X":295,"Y":238,"Color":"0x0000FF","Rotation":0,"Type":0,"HoldNumber":null,"Direction":0,"DirectionString":"N"},{"Id":0,"Holdset":null,"Description":null,"X":295,"Y":88,"Color":"0xFF0000","Rotation":0,"Type":0,"HoldNumber":null,"Direction":0,"DirectionString":"N"},{"Id":0,"Holdset":null,"Description":null,"X":345,"Y":736,"Color":"0x00FF00","Rotation":0,"Type":0,"HoldNumber":null,"Direction":0,"DirectionString":"N"},{"Id":0,"Holdset":null,"Description":null,"X":395,"Y":338,"Color":"0x0000FF","Rotation":0,"Type":0,"HoldNumber":null,"Direction":0,"DirectionString":"N"},{"Id":0,"Holdset":null,"Description":null,"X":445,"Y":586,"Color":"0x0000FF","Rotation":0,"Type":0,"HoldNumber":null,"Direction":0,"DirectionString":"N"},{"Id":0,"Holdset":null,"Description":null,"X":495,"Y":788,"Color":"0x00FF00","Rotation":0,"Type":0,"HoldNumber":null,"Direction":0,"DirectionString":"N"}],"RepeatText":"204 climbers  have repeated this problem","NumberOfTries":"FLASHED","NameForUrl":"russel","Id":36607,"ApiId":36607,"DateInserted":"\/Date(1472981613000)\/","DateUpdated":null,"DateDeleted":null,"DateTimeString":"04 Sep 2016 10:33"},"Attempts":0,"Grade":"6B+","NumberOfTries":"Flashed","Rating":0,"DateClimbed":"\/Date(1500505200000)\/","DateClimbedAsString":"20 Jul 2017","DateInserted":"\/Date(1500597207000)\/","Comment":"","User":{"Id":"6BE4A8C1-02C7-4BA4-9589-769ED0B3571C","Nickname":"Sean Christopherson","Firstname":"Sean","Lastname":"Christopherson","City":"Portland","Country":"USA","ProfileImageUrl":"/Content/Account/Images/default-profile.png?636442311929123653"}},{"Id":2410430,"Problem":{"Method":"Feet follow hands","Name":"THE WALTZ","Grade":"6B+","UserGrade":"6B+","MoonBoardConfiguration":null,"MoonBoardConfigurationId":0,"Setter":{"Id":"5D88E965-7AB8-4D3E-8821-150CC3ED14A4","Nickname":"Edvard Raft","Firstname":"Edvard","Lastname":"Raft","City":"Stockholm","Country":"SWEDEN","ProfileImageUrl":"/Content/Account/Images/default-profile.png?636442311929123653"},"FirstAscender":false,"Rating":0,"UserRating":2,"Repeats":220,"Attempts":0,"Holdsetup":{"Id":1,"Description":"MoonBoard 2016","Setby":null,"DateInserted":null,"DateUpdated":null,"DateDeleted":null,"Holdsets":null,"MoonBoardConfigurations":null,"HoldLayoutId":0,"AllowClimbMethods":false},"IsBenchmark":false,"Moves":[{"Id":1529021,"Description":"F5","IsStart":true,"IsEnd":false},{"Id":1529022,"Description":"C8","IsStart":false,"IsEnd":false},{"Id":1529023,"Description":"G9","IsStart":false,"IsEnd":false},{"Id":1529024,"Description":"B11","IsStart":false,"IsEnd":false},{"Id":1529025,"Description":"G13","IsStart":false,"IsEnd":false},{"Id":1529026,"Description":"E15","IsStart":false,"IsEnd":false},{"Id":1529027,"Description":"G18","IsStart":false,"IsEnd":true}],"Holdsets":null,"Locations":[{"Id":0,"Holdset":null,"Description":null,"X":145,"Y":436,"Color":"0x0000FF","Rotation":0,"Type":0,"HoldNumber":null,"Direction":0,"DirectionString":"N"},{"Id":0,"Holdset":null,"Description":null,"X":195,"Y":588,"Color":"0x0000FF","Rotation":0,"Type":0,"HoldNumber":null,"Direction":0,"DirectionString":"N"},{"Id":0,"Holdset":null,"Description":null,"X":295,"Y":238,"Color":"0x0000FF","Rotation":0,"Type":0,"HoldNumber":null,"Direction":0,"DirectionString":"N"},{"Id":0,"Holdset":null,"Description":null,"X":345,"Y":736,"Color":"0x00FF00","Rotation":0,"Type":0,"HoldNumber":null,"Direction":0,"DirectionString":"N"},{"Id":0,"Holdset":null,"Description":null,"X":395,"Y":538,"Color":"0x0000FF","Rotation":0,"Type":0,"HoldNumber":null,"Direction":0,"DirectionString":"N"},{"Id":0,"Holdset":null,"Description":null,"X":395,"Y":338,"Color":"0x0000FF","Rotation":0,"Type":0,"HoldNumber":null,"Direction":0,"DirectionString":"N"},{"Id":0,"Holdset":null,"Description":null,"X":395,"Y":88,"Color":"0xFF0000","Rotation":0,"Type":0,"HoldNumber":null,"Direction":0,"DirectionString":"N"}],"RepeatText":"220 climbers  have repeated this problem","NumberOfTries":"FLASHED","NameForUrl":"the-waltz","Id":43026,"ApiId":43026,"DateInserted":"\/Date(1474995097000)\/","DateUpdated":null,"DateDeleted":null,"DateTimeString":"27 Sep 2016 17:51"},"Attempts":0,"Grade":"6B+","NumberOfTries":"Flashed","Rating":2,"DateClimbed":"\/Date(1500505200000)\/","DateClimbedAsString":"20 Jul 2017","DateInserted":"\/Date(1500745409000)\/","Comment":"","User":{"Id":"6BE4A8C1-02C7-4BA4-9589-769ED0B3571C","Nickname":"Sean Christopherson","Firstname":"Sean","Lastname":"Christopherson","City":"Portland","Country":"USA","ProfileImageUrl":"/Content/Account/Images/default-profile.png?636442311929279916"}},{"Id":2410431,"Problem":{"Method":"Feet follow hands","Name":"WARMUP","Grade":"6B+","UserGrade":"6B+","MoonBoardConfiguration":null,"MoonBoardConfigurationId":0,"Setter":{"Id":"D42A315F-D0FF-426F-B94B-32970BFA5E56","Nickname":"Randolph Möllenberg","Firstname":"Randolph","Lastname":"Möllenberg","City":"Munich","Country":"GERMANY","ProfileImageUrl":"/Content/Account/Images/default-profile.png?636442311929279916"},"FirstAscender":false,"Rating":0,"UserRating":2,"Repeats":226,"Attempts":0,"Holdsetup":{"Id":1,"Description":"MoonBoard 2016","Setby":null,"DateInserted":null,"DateUpdated":null,"DateDeleted":null,"Holdsets":null,"MoonBoardConfigurations":null,"HoldLayoutId":0,"AllowClimbMethods":false},"IsBenchmark":false,"Moves":[{"Id":1529890,"Description":"F5","IsStart":true,"IsEnd":false},{"Id":1529891,"Description":"G8","IsStart":false,"IsEnd":false},{"Id":1529892,"Description":"E10","IsStart":false,"IsEnd":false},{"Id":1529893,"Description":"G13","IsStart":false,"IsEnd":false},{"Id":1529894,"Description":"E15","IsStart":false,"IsEnd":false},{"Id":1529895,"Description":"G18","IsStart":false,"IsEnd":true}],"Holdsets":null,"Locations":[{"Id":0,"Holdset":null,"Description":null,"X":295,"Y":488,"Color":"0x0000FF","Rotation":0,"Type":0,"HoldNumber":null,"Direction":0,"DirectionString":"N"},{"Id":0,"Holdset":null,"Description":null,"X":295,"Y":238,"Color":"0x0000FF","Rotation":0,"Type":0,"HoldNumber":null,"Direction":0,"DirectionString":"N"},{"Id":0,"Holdset":null,"Description":null,"X":345,"Y":736,"Color":"0x00FF00","Rotation":0,"Type":0,"HoldNumber":null,"Direction":0,"DirectionString":"N"},{"Id":0,"Holdset":null,"Description":null,"X":395,"Y":588,"Color":"0x0000FF","Rotation":0,"Type":0,"HoldNumber":null,"Direction":0,"DirectionString":"N"},{"Id":0,"Holdset":null,"Description":null,"X":395,"Y":338,"Color":"0x0000FF","Rotation":0,"Type":0,"HoldNumber":null,"Direction":0,"DirectionString":"N"},{"Id":0,"Holdset":null,"Description":null,"X":395,"Y":88,"Color":"0xFF0000","Rotation":0,"Type":0,"HoldNumber":null,"Direction":0,"DirectionString":"N"}],"RepeatText":"226 climbers  have repeated this problem","NumberOfTries":"FLASHED","NameForUrl":"warmup","Id":45381,"ApiId":45381,"DateInserted":"\/Date(1475686670000)\/","DateUpdated":null,"DateDeleted":null,"DateTimeString":"05 Oct 2016 17:57"},"Attempts":0,"Grade":"6B+","NumberOfTries":"Flashed","Rating":0,"DateClimbed":"\/Date(1500505200000)\/","DateClimbedAsString":"20 Jul 2017","DateInserted":"\/Date(1500745688000)\/","Comment":"","User":{"Id":"6BE4A8C1-02C7-4BA4-9589-769ED0B3571C","Nickname":"Sean Christopherson","Firstname":"Sean","Lastname":"Christopherson","City":"Portland","Country":"USA","ProfileImageUrl":"/Content/Account/Images/default-profile.png?636442311929436178"}}],"Total":6,"AggregateResults":null,"Errors":null}