{"Data":[{"Id":2332730,"Problem":{"Method":"Feet follow hands","Name":"JORDAN2","Grade":"7B","UserGrade":"7B","MoonBoardConfiguration":null,"MoonBoardConfigurationId":0,"Setter":{"Id":"23A61F36-D9DD-4814-BB6F-3B84E9D62AD8","Nickname":"joohun kim","Firstname":"joohun","Lastname":"kim","City":"sokcho","Country":"S.KOREA","ProfileImageUrl":"/Content/Account/Images/default-profile.png?636442311436867612"},"FirstAscender":false,"Rating":0,"UserRating":3,"Repeats":362,"Attempts":0,"Holdsetup":{"Id":1,"Description":"MoonBoard 2016","Setby":null,"DateInserted":null,"DateUpdated":null,"DateDeleted":null,"Holdsets":null,"MoonBoardConfigurations":null,"HoldLayoutId":0,"AllowClimbMethods":false},"IsBenchmark":false,"Moves":[{"Id":1534244,"Description":"K5","IsStart":true,"IsEnd":false},{"Id":1534245,"Description":"G6","IsStart":true,"IsEnd":false},{"Id":1534246,"Description":"H8","IsStart":false,"IsEnd":false},{"Id":1534247,"Description":"G9","IsStart":false,"IsEnd":false},{"Id":1534248,"Description":"E12","IsStart":false,"IsEnd":false},{"Id":1534249,"Description":"B15","IsStart":false,"IsEnd":false},{"Id":1534250,"Description":"G17","IsStart":false,"IsEnd":false},{"Id":1534251,"Description":"G18","IsStart":false,"IsEnd":true}],"Holdsets":null,"Locations":[{"Id":0,"Holdset":null,"Description":null,"X":145,"Y":236,"Color":"0x0000FF","Rotation":0,"Type":0,"HoldNumber":null,"Direction":0,"DirectionString":"N"},{"Id":0,"Holdset":null,"Description":null,"X":295,"Y":388,"Color":"0x0000FF","Rotation":0,"Type":0,"HoldNumber":null,"Direction":0,"DirectionString":"N"},{"Id":0,"Holdset":null,"Description":null,"X":395,"Y":688,"Color":"0x00FF00","Rotation":0,"Type":0,"HoldNumber":null,"Direction":0,"DirectionString":"N"},{"Id":0,"Holdset":null,"Description":null,"X":395,"Y":538,"Color":"0x0000FF","Rotation":0,"Type":0,"HoldNumber":null,"Direction":0,"DirectionString":"N"},{"Id":0,"Holdset":null,"Description":null,"X":395,"Y":138,"Color":"0x0000FF","Rotation":0,"Type":0,"HoldNumber":null,"Direction":0,"DirectionString":"N"},{"Id":0,"Holdset":null,"Description":null,"X":395,"Y":88,"Color":"0xFF0000","Rotation":0,"Type":0,"HoldNumber":null,"Direction":0,"DirectionString":"N"},{"Id":0,"Holdset":null,"Description":null,"X":445,"Y":586,"Color":"0x0000FF","Rotation":0,"Type":0,"HoldNumber":null,"Direction":0,"DirectionString":"N"},{"Id":0,"Holdset":null,"Description":null,"X":595,"Y":738,"Color":"0x00FF00","Rotation":0,"Type":0,"HoldNumber":null,"Direction":0,"DirectionString":"N"}],"RepeatText":"362 climbers  have repeated this problem","NumberOfTries":"MORE THAN 3 TRIES","NameForUrl":"jordan2","Id":58287,"ApiId":58287,"DateInserted":"\/Date(1478776642000)\/","DateUpdated":null,"DateDeleted":null,"DateTimeString":"10 Nov 2016 11:17"},"Attempts":0,"Grade":"7A+","NumberOfTries":"more than 3 tries","Rating":3,"DateClimbed":"\/Date(1489881600000)\/","DateClimbedAsString":"19 Mar 2017","DateInserted":"\/Date(1489947368000)\/","Comment":"","User":{"Id":"6BE4A8C1-02C7-4BA4-9589-769ED0B3571C","Nickname":"Sean Christopherson","Firstname":"Sean","Lastname":"Christopherson","City":"Portland","Country":"USA","ProfileImageUrl":"/Content/Account/Images/default-profile.png?636442311437180133"}}],"Total":1,"AggregateResults":null,"Errors":null}